fetch_meditation/__init__.py
fetch_meditation/english_jft.py
fetch_meditation/english_spad.py
fetch_meditation/french_jft.py
fetch_meditation/german_jft.py
fetch_meditation/italian_jft.py
fetch_meditation/japanese_jft.py
fetch_meditation/jft.py
fetch_meditation/jft_entry.py
fetch_meditation/jft_language.py
fetch_meditation/jft_settings.py
fetch_meditation/portuguese_jft.py
fetch_meditation/russian_jft.py
fetch_meditation/spad.py
fetch_meditation/spad_entry.py
fetch_meditation/spad_language.py
fetch_meditation/spad_settings.py
fetch_meditation/spanish_jft.py
fetch_meditation/swedish_jft.py
fetch_meditation/tests/__init__.py
fetch_meditation/tests/test_english_jft_with_timezone.py
fetch_meditation/tests/test_english_spad_with_timezone.py
fetch_meditation/tests/test_jft.py
fetch_meditation/tests/test_jft_entry.py
fetch_meditation/tests/test_jft_settings.py
fetch_meditation/tests/test_spad.py
fetch_meditation/tests/test_spad_entry.py
fetch_meditation/tests/test_spad_settings.py
fetch_meditation/utilities/http_utility.py
fetch_meditation-0.4.0.dist-info/METADATA
fetch_meditation-0.4.0.dist-info/WHEEL
fetch_meditation-0.4.0.dist-info/RECORD
