Metadata-Version: 2.3
Name: fetch-meditation
Version: 0.4.0
Summary: Fetch Daily meditations
License: MIT
Author: BMLT Authors
Author-email: help@bmlt.app
Requires-Python: >=3.11,<4.0
Classifier: License :: OSI Approved :: MIT License
Classifier: Programming Language :: Python :: 3
Classifier: Programming Language :: Python :: 3.11
Classifier: Programming Language :: Python :: 3.12
Classifier: Programming Language :: Python :: 3.13
Requires-Dist: beautifulsoup4 (>=4.12.2,<5.0.0)
Requires-Dist: pytz (>=2023.3,<2024.0)
Requires-Dist: sphinx-rtd-theme (>=3.0.2,<4.0.0)
Requires-Dist: urllib3 (>=2.0.7,<3.0.0)
